<word pos="PRON" lemma="það" />það</word>
<word pos="DET" lemma="allur" />öllum</word>
<word pos="VERB" lemma="auðsýna" />auðsýnt</word>
<word pos="SCONJ" lemma="að" />að</word>
<word pos="ADV" lemma="mjög" />mjög</word>
<word pos="AUX" lemma="munu" />mundi</word>
<word pos="VERB" lemma="vanmeta" />vanmeta</word>
<word pos="AUX" lemma="vera" />verið</word>
<word pos="AUX" lemma="hafa" />hafa</word>
<word pos="PUNCT" lemma="." />.</word>
<word pos="AUX" lemma="vera" />Var</word>
<word pos="ADV" lemma="þá" />þá</word>
<word pos="VERB" lemma="lýsa" />lýst</word>
<word pos="DET" lemma="sá" />þeirri</word>
<word pos="NOUN" lemma="jarteinn" />jartein</word>
<word pos="ADP" lemma="í" />í</word>
<word pos="NOUN" lemma="kirkja" />kirkju</word>
<word pos="CCONJ" lemma="og" />og</word>
<word pos="VERB" lemma="syngja" />sungið</word>
<word pos="X" lemma="te" />Te</word>
<word pos="X" lemma="deum" />deum</word>
<word pos="CCONJ" lemma="og" />og</word>
<word pos="VERB" lemma="hringja" />hringt</word>
<word pos="DET" lemma="allur" />öllum</word>
<word pos="NOUN" lemma="klukka" />klukkum</word>
<word pos="CCONJ" lemma="og" />og</word>
<word pos="VERB" lemma="lofa" />lofuðu</word>
<word pos="DET" lemma="allur" />allir</word>
<word pos="PROPN" lemma="guð" />guð</word>
<word pos="SCONJ" lemma="sem" />sem</word>
<word pos="VERB" lemma="kunna" />kunnu</word>
<word pos="ADV" lemma="framar" />framast</word>
<word pos="CCONJ" lemma="og" />og</word>
<word pos="DET" lemma="hinn" />hinn</word>
<word pos="ADJ" lemma="sæll" />sæla</word>
<word pos="PROPN" lemma="þorlákur" />Þorlák</word>
<word pos="NOUN" lemma="biskup" />biskup</word>
<word pos="PUNCT" lemma="." />.</word>
<word pos="ADP" lemma="í" />Í</word>
<word pos="NOUN" lemma="ölfus" />Ölfusi</word>
<word pos="VERB" lemma="verða" />varð</word>
<word pos="DET" lemma="sá" />sá</word>
<word pos="NOUN" lemma="atburður" />atburður</word>
<word pos="SCONJ" lemma="að" />að</word>
<word pos="NOUN" lemma="maður" />maður</word>
<word pos="VERB" lemma="meiða" />meiddist</word>
<word pos="ADP" lemma="í" />í</word>
<word pos="NOUN" lemma="leikur" />leik</word>
<word pos="CCONJ" lemma="og" />og</word>
<word pos="VERB" lemma="ganga" />gekk</word>
<word pos="NOUN" lemma="hönd" />hönd</word>
<word pos="PRON" lemma="hann" />hans</word>
<word pos="ADP" lemma="úr" />úr</word>
<word pos="NOUN" lemma="liður" />liði</word>
<word pos="CCONJ" lemma="og" />og</word>
<word pos="VERB" lemma="þurfa" />þurfti</word>
<word pos="DET" lemma="margur" />marga</word>
<word pos="NOUN" lemma="maður" />menn</word>
<word pos="ADP" lemma="til" />til</word>
<word pos="ADV" lemma="áður" />áður</word>
<word pos="ADP" lemma="í" />í</word>
<word pos="NOUN" lemma="liður" />liðinn</word>
<word pos="VERB" lemma="koma" />kæmist</word>
<word pos="PUNCT" lemma="." />.</word>
<word pos="ADV" lemma="síðan" />Síðan</word>
<word pos="VERB" lemma="fara" />fór</word>
<word pos="PRON" lemma="hann" />hann</word>
<word pos="ADV" lemma="heim" />heim</word>
<word pos="ADP" lemma="of" />of</word>
<word pos="NOUN" lemma="aftan" />aftaninn</word>
<word pos="PUNCT" lemma="." />.</word>
<word pos="CCONJ" lemma="en" />En</word>
<word pos="ADP" lemma="of" />of</word>
<word pos="NOUN" lemma="morgunn" />morgininn</word>
<word pos="ADV" lemma="eftir" />eftir</word>
<word pos="VERB" lemma="ljósta" />laust</word>
<word pos="NOUN" lemma="æðiverk" />æðiverk</word>
<word pos="ADP" lemma="í" />í</word>
<word pos="NOUN" lemma="hönd" />höndina</word>
<word pos="ADP" lemma="svo" />svo</word>
<word pos="SCONJ" lemma="að" />að</word>
<word pos="PRON" lemma="hann" />hann</word>
<word pos="AUX" lemma="mega" />mátti</word>
<word pos="ADV" lemma="ekki" />ekki</word>
<word pos="VERB" lemma="sofa" />sofa</word>
<word pos="CCONJ" lemma="og" />og</word>
<word pos="PRON" lemma="hann" />hann</word>
<word pos="VERB" lemma="fá" />fékk</word>
<word pos="ADJ" lemma="trauður" />trautt</word>
<word pos="X" lemma="legró" />legró</word>
<word pos="PUNCT" lemma="." />.</word>
<word pos="VERB" lemma="heita" />Hét</word>
<word pos="PRON" lemma="hann" />hann</word>
<word pos="ADV" lemma="síðan" />síðan</word>
<word pos="ADP" lemma="af" />af</word>
<word pos="DET" lemma="allur" />öllum</word>
<word pos="NOUN" lemma="hugur" />hug</word>
<word pos="ADP" lemma="á" />á</word>
<word pos="DET" lemma="hinn" />hinn</word>
<word pos="ADJ" lemma="sæll" />sæla</word>
<word pos="PROPN" lemma="þorlákur" />Þorlák</word>
<word pos="NOUN" lemma="biskup" />biskup</word>
<word pos="ADP" lemma="til" />til</word>
<word pos="NOUN" lemma="hjálp" />hjálpar</word>
<word pos="PRON" lemma="sig" />sér</word>
<word pos="CCONJ" lemma="og" />og</word>
<word pos="NOUN" lemma="heilsubót" />heilsubótar</word>
<word pos="PUNCT" lemma="." />.</word>
<word pos="ADP" lemma="eftir" />Eftir</word>
<word pos="PRON" lemma="það" />það</word>
<word pos="VERB" lemma="renna" />rann</word>
<word pos="ADP" lemma="á" />á</word>
<word pos="PRON" lemma="hann" />hann</word>
<word pos="NOUN" lemma="höfgi" />höfgi</word>
<word pos="CCONJ" lemma="og" />og</word>
<word pos="VERB" lemma="sjá" />sá</word>
<word pos="PRON" lemma="hann" />hann</word>
<word pos="ADV" lemma="síðan" />síðan</word>
<word pos="ADP" lemma="í" />í</word>
<word pos="DET" lemma="sá" />þeim</word>
<word pos="NOUN" lemma="höfgi" />höfga</word>
<word pos="DET" lemma="hinn" />hinn</word>
<word pos="ADJ" lemma="sæll" />sæla</word>
<word pos="PROPN" lemma="þorlákur" />Þorlák</word>
<word pos="NOUN" lemma="biskup" />biskup</word>
<word pos="CCONJ" lemma="og" />og</word>
<word pos="VERB" lemma="mæla" />mælti</word>
<word pos="ADP" lemma="við" />við</word>
<word pos="PRON" lemma="hann" />hann</word>
<word pos="CCONJ" lemma="og" />og</word>
<word pos="VERB" lemma="taka" />tók</word>
<word pos="ADV" lemma="ekki" />eigi</word>
<word pos="ADP" lemma="á" />á</word>
<word pos="PRON" lemma="hann" />honum</word>
<word pos="PUNCT" lemma="." />.</word>
<word pos="PUNCT" lemma=""" />"</word>
<word pos="ADJ" lemma="tíður" />Títt</word>
<word pos="VERB" lemma="gera" />gerist</word>
<word pos="PRON" lemma="þú" />yður</word>
<word pos="ADV" lemma="nú" />nú</word>
<word pos="PUNCT" lemma=""" />"</word>
<word pos="PUNCT" lemma="," />,</word>
<word pos="VERB" lemma="segja" />sagði</word>
<word pos="PRON" lemma="hann" />hann</word>
<word pos="PUNCT" lemma="," />,</word>
<word pos="PUNCT" lemma=""" />"</word>
<word pos="PART" lemma="að" />að</word>
<word pos="VERB" lemma="heita" />heita</word>
<word pos="ADP" lemma="á" />á</word>
<word pos="NOUN" lemma="leið" />leið</word>
<word pos="ADP" lemma="fram" />fram</word>
<word pos="CCONJ" lemma="og" />og</word>
<word pos="VERB" lemma="enda" />enda</word>
<word pos="ADV" lemma="ekki" />eigi</word>
<word pos="PRON" lemma="það" />það</word>
<word pos="SCONJ" lemma="er" />er</word>
<word pos="PRON" lemma="þú" />þér</word>
<word pos="VERB" lemma="heita" />heitið</word>
<word pos="PUNCT" lemma="." />.</word>
<word pos="PUNCT" lemma=""" />"</word>
<word pos="ADV" lemma="síðan" />Síðan</word>
<word pos="VERB" lemma="vakna" />vaknaði</word>
<word pos="PRON" lemma="hann" />hann</word>
<word pos="CCONJ" lemma="og" />og</word>
<word pos="AUX" lemma="vera" />var</word>
<word pos="ADV" lemma="þá" />þá</word>
<word pos="ADJ" lemma="alheill" />alheill</word>
<word pos="CCONJ" lemma="og" />og</word>
<word pos="VERB" lemma="minna" />minntist</word>
<word pos="ADP" lemma="á" />á</word>
<word pos="ADV" lemma="síðan" />síðan</word>
<word pos="ADP" lemma="í" />í</word>
<word pos="NOUN" lemma="hugur" />hug</word>
<word pos="PRON" lemma="sig" />sér</word>
<word pos="ADV" lemma="hví" />hví</word>
<word pos="DET" lemma="hinn" />hinn</word>
<word pos="ADJ" lemma="sæll" />sæli</word>
<word pos="PROPN" lemma="þorlákur" />Þorlákur</word>
<word pos="NOUN" lemma="biskup" />biskup</word>
<word pos="AUX" lemma="munu" />mundi</word>
<word pos="DET" lemma="sá" />þann</word>
<word pos="NOUN" lemma="ákenning" />ákenning</word>
<word pos="VERB" lemma="gera" />gert</word>
<word pos="AUX" lemma="hafa" />hafa</word>
<word pos="ADP" lemma="of" />of</word>
<word pos="NOUN" lemma="heit" />heit</word>
<word pos="PRON" lemma="hann" />hans</word>
<word pos="CCONJ" lemma="og" />og</word>
<word pos="VERB" lemma="munu" />mundi</word>
<word pos="ADV" lemma="þá" />þá</word>
<word pos="ADV" lemma="síðan" />síðan</word>
<word pos="SCONJ" lemma="að" />að</word>
<word pos="PRON" lemma="hann" />hann</word>
<word pos="AUX" lemma="hafa" />hafði</word>
<word pos="VERB" lemma="heita" />heitið</word>
<word pos="ADP" lemma="á" />á</word>
<word pos="DET" lemma="hinn" />hinn</word>
<word pos="ADJ" lemma="sæll" />sæla</word>
<word pos="PROPN" lemma="þorlákur" />Þorlák</word>
<word pos="NOUN" lemma="biskup" />biskup</word>
<word pos="ADP" lemma="of" />of</word>
<word pos="NOUN" lemma="sumar" />sumarið</word>
<word pos="ADV" lemma="áður" />áður</word>
<word pos="ADP" lemma="fyrir" />fyrir</word>
<word pos="NOUN" lemma="auga" />augum</word>
<word pos="NOUN" lemma="bróðir" />bróður</word>
<word pos="PRON" lemma="sinn" />síns</word>
<word pos="CCONJ" lemma="en" />en</word>
<word pos="AUX" lemma="hafa" />hafði</word>
<word pos="ADV" lemma="ekki" />eigi</word>
<word pos="ADP" lemma="í" />í</word>
<word pos="NOUN" lemma="hugur" />hug</word>
<word pos="VERB" lemma="koma" />komið</word>
<word pos="PART" lemma="að" />að</word>
<word pos="VERB" lemma="enda" />enda</word>
<word pos="PUNCT" lemma="." />.</word>
<word pos="VERB" lemma="senda" />Sendi</word>
<word pos="PRON" lemma="hann" />hann</word>
<word pos="ADV" lemma="síðan" />síðan</word>
<word pos="ADP" lemma="í" />í</word>
<word pos="PROPN" lemma="skálaholt" />Skálaholt</word>
<word pos="DET" lemma="hvort" />hvort</word>
<word pos="NUM" lemma="tveir" />tveggja</word>
<word pos="NOUN" lemma="heitfé" />heitfé</word>
<word pos="CCONJ" lemma="og" />og</word>
<word pos="VERB" lemma="verða" />urðu</word>
<word pos="DET" lemma="allur" />allir</word>
<word pos="ADJ" lemma="feginn" />fegnir</word>
<word pos="SCONJ" lemma="er" />er</word>
<word pos="DET" lemma="þessi" />þessa</word>
<word pos="NOUN" lemma="jarteinn" />jartein</word>
<word pos="VERB" lemma="heyra" />heyrðu</word>
<word pos="VERB" lemma="segja" />sagða</word>
<word pos="CCONJ" lemma="og" />og</word>
<word pos="VERB" lemma="gera" />gerðu</word>
<word pos="PROPN" lemma="guð" />guði</word>
<word pos="NOUN" lemma="þökk" />þakkir</word>
<word pos="CCONJ" lemma="og" />og</word>
<word pos="ADJ" lemma="sæll" />sælum</word>
<word pos="PROPN" lemma="þorlákur" />Þorláki</word>
<word pos="NOUN" lemma="biskup" />biskupi</word>
<word pos="PUNCT" lemma="." />.</word>
<word pos="ADP" lemma="á" />Á</word>
<word pos="NOUN" lemma="bær" />bæ</word>
<word pos="DET" lemma="einn" />einum</word>
<word pos="AUX" lemma="vera" />var</word>
<word pos="ADJ" lemma="griðungur" />griðungur</word>
<word pos="NOUN" lemma="mannýgur" />mannýgur</word>
<word pos="DET" lemma="sá" />sá</word>
<word pos="SCONJ" lemma="er" />er</word>
<word pos="ADV" lemma="trautt" />trautt</word>
<word pos="AUX" lemma="mega" />máttu</word>
<word pos="NOUN" lemma="karl" />karlar</word>
<word pos="VERB" lemma="reka" />reka</word>
<word pos="NOUN" lemma="naut" />naut</word>
<word pos="ADP" lemma="fyrir" />fyrir</word>
<word pos="PRON" lemma="hann" />honum</word>
<word pos="PUNCT" lemma="." />.</word>
<word pos="CCONJ" lemma="en" />En</word>
<word pos="ADV" lemma="þá" />þá</word>
<word pos="VERB" lemma="bera" />barst</word>
<word pos="ADV" lemma="svo" />svo</word>
<word pos="ADP" lemma="að" />að</word>
<word pos="SCONJ" lemma="að" />að</word>
<word pos="DET" lemma="enginn" />engi</word>
<word pos="NOUN" lemma="karlmaður" />karlmaður</word>
<word pos="AUX" lemma="vera" />var</word>
<word pos="ADP" lemma="á" />á</word>
<word pos="NOUN" lemma="bær" />bænum</word>
<word pos="CCONJ" lemma="en" />en</word>
<word pos="NOUN" lemma="nauti" />nautin</word>
<word pos="VERB" lemma="þurfa" />þurfti</word>
<word pos="ADV" lemma="heim" />heim</word>
<word pos="PART" lemma="að" />að</word>
<word pos="VERB" lemma="reka" />reka</word>
<word pos="PUNCT" lemma="." />.</word>
<word pos="VERB" lemma="verða" />Varð</word>
<word pos="ADV" lemma="síðan" />síðan</word>
<word pos="ADP" lemma="til" />til</word>
<word pos="NOUN" lemma="kona" />kona</word>
<word pos="DET" lemma="einn" />ein</word>
<word pos="ADV" lemma="vel" />vel</word>
<word pos="ADJ" lemma="tvítugur" />tvítug</word>
<word pos="PUNCT" lemma="," />,</word>
<word pos="ADV" lemma="heldur" />heldur</word>
<word pos="ADJ" lemma="knár" />kná</word>
<word pos="PUNCT" lemma="," />,</word>
<word pos="CCONJ" lemma="og" />og</word>
<word pos="ADV" lemma="vel" />vel</word>
<word pos="ADJ" lemma="viskur" />visk</word>
<word pos="PART" lemma="að" />að</word>
<word pos="VERB" lemma="fara" />fara</word>
<word pos="ADP" lemma="eftir" />eftir</word>
<word pos="NOUN" lemma="naut" />nautum</word>
<word pos="CCONJ" lemma="og" />og</word>
<word pos="VERB" lemma="hafa" />hafði</word>
<word pos="NOUN" lemma="stafur" />staf</word>
<word pos="ADP" lemma="í" />í</word>
<word pos="NOUN" lemma="hönd" />hendi</word>
<word pos="PUNCT" lemma="." />.</word>
<word pos="CCONJ" lemma="en" />En</word>
<word pos="SCONJ" lemma="er" />er</word>
<word pos="PRON" lemma="hún" />hún</word>
<word pos="VERB" lemma="koma" />kom</word>
<word pos="ADP" lemma="í" />í</word>
<word pos="NOUN" lemma="nánd" />nánd</word>
<word pos="ADP" lemma="við" />við</word>
<word pos="NOUN" lemma="naut" />nautin</word>
<word pos="PUNCT" lemma="," />,</word>
<word pos="ADV" lemma="þá" />þá</word>
<word pos="VERB" lemma="gera" />gerði</word>
<word pos="NOUN" lemma="griðungur" />griðungurinn</word>
<word pos="ADP" lemma="á" />á</word>
<word pos="NOUN" lemma="mót" />mót</word>
<word pos="PRON" lemma="hún" />henni</word>
<word pos="PUNCT" lemma="." />.</word>
<word pos="CCONJ" lemma="en" />En</word>
<word pos="PRON" lemma="hún" />hún</word>
<word pos="VERB" lemma="ljósta" />laust</word>
<word pos="PRON" lemma="hann" />hann</word>
<word pos="ADV" lemma="síðan" />síðan</word>
<word pos="ADV" lemma="þegar" />þegar</word>
<word pos="ADP" lemma="með" />með</word>
<word pos="NOUN" lemma="stafur" />stafnum</word>
<word pos="PUNCT" lemma="." />.</word>
<word pos="CCONJ" lemma="en" />En</word>
<word pos="NOUN" lemma="griðungur" />griðungurinn</word>
<word pos="VERB" lemma="ganga" />gekk</word>
<word pos="ADV" lemma="ekki" />eigi</word>
<word pos="ADV" lemma="undan" />undan</word>
<word pos="CCONJ" lemma="og" />og</word>
<word pos="AUX" lemma="vilja" />vildi</word>
<word pos="VERB" lemma="stanga" />stanga</word>
<word pos="PRON" lemma="hún" />hana</word>
<word pos="PUNCT" lemma="." />.</word>
<word pos="CCONJ" lemma="en" />En</word>
<word pos="PRON" lemma="hún" />hún</word>
<word pos="VERB" lemma="verða" />varð</word>
<word pos="ADP" lemma="á" />á</word>
<word pos="ADP" lemma="milli" />milli</word>
<word pos="NOUN" lemma="horn" />hornanna</word>
<word pos="NOUN" lemma="griðungur" />griðungsins</word>
<word pos="CCONJ" lemma="og" />og</word>
<word pos="VERB" lemma="taka" />tók</word>
<word pos="ADV" lemma="síðan" />síðan</word>
<word pos="NOUN" lemma="hönd" />höndum</word>
<word pos="ADP" lemma="of" />of</word>
<word pos="NOUN" lemma="háls" />háls</word>
<word pos="NOUN" lemma="griðungur" />griðunginum</word>
<word pos="CCONJ" lemma="og" />og</word>
<word pos="VERB" lemma="halda" />hélt</word>
<word pos="PRON" lemma="sig" />sér</word>
<word pos="ADV" lemma="svo" />svo</word>
<word pos="PUNCT" lemma="." />.</word>
<word pos="CCONJ" lemma="en" />En</word>
<word pos="NOUN" lemma="griðungur" />griðungurinn</word>
<word pos="AUX" lemma="vilja" />vildi</word>
<word pos="PRON" lemma="hún" />hana</word>
<word pos="ADV" lemma="ávallt" />ávallt</word>
<word pos="ADV" lemma="ofan" />ofan</word>
<word pos="VERB" lemma="færa" />færa</word>
<word pos="PUNCT" lemma="." />.</word>
<word pos="PRON" lemma="hún" />Hún</word>
<word pos="VERB" lemma="taka" />tók</word>
<word pos="ADV" lemma="þá" />þá</word>
<word pos="ADV" lemma="síðan" />síðan</word>
<word pos="PART" lemma="að" />að</word>
<word pos="VERB" lemma="mæða" />mæðast</word>
<word pos="ADV" lemma="mjög" />mjög</word>
<word pos="CCONJ" lemma="og" />og</word>
<word pos="AUX" lemma="vera" />var</word>
<word pos="ADV" lemma="þá" />þá</word>
<word pos="ADP" lemma="við" />við</word>
<word pos="PRON" lemma="sjálfur" />sjálft</word>
<word pos="SCONJ" lemma="að" />að</word>
<word pos="PRON" lemma="hún" />hún</word>
<word pos="AUX" lemma="munu" />mundi</word>
<word pos="VERB" lemma="verða" />verða</word>
<word pos="ADV" lemma="laust" />laust</word>
<word pos="PART" lemma="að" />að</word>
<word pos="VERB" lemma="láta" />láta</word>
<word pos="PUNCT" lemma="." />.</word>
<word pos="VERB" lemma="þykja" />Þóttist</word>
<word pos="PRON" lemma="hún" />hún</word>
<word pos="ADV" lemma="þá" />þá</word>
<word pos="VERB" lemma="ráða" />ráðin</word>
<word pos="ADP" lemma="til" />til</word>
<word pos="NOUN" lemma="örkumli" />örkumla</word>
<word pos="CCONJ" lemma="eða" />eða</word>
<word pos="ADP" lemma="til" />til</word>
<word pos="NOUN" lemma="bani" />bana</word>
<word pos="PRON" lemma="það" />því</word>
<word pos="SCONJ" lemma="að" />að</word>
<word pos="PRON" lemma="hún" />hún</word>
<word pos="VERB" lemma="finna" />fann</word>
<word pos="ADV" lemma="ekki" />eigi</word>
<word pos="SCONJ" lemma="að" />að</word>
<word pos="NOUN" lemma="griðungur" />griðungurinn</word>
<word pos="VERB" lemma="mæða" />mæddist</word>
<word pos="PUNCT" lemma="." />.</word>
<word pos="VERB" lemma="heita" />Hét</word>
<word pos="PRON" lemma="hún" />hún</word>
<word pos="ADV" lemma="þá" />þá</word>
<word pos="ADV" lemma="síðan" />síðan</word>
<word pos="ADP" lemma="á" />á</word>
<word pos="DET" lemma="hinn" />hinn</word>
<word pos="ADJ" lemma="sæll" />sæla</word>
<word pos="PROPN" lemma="þorlákur" />Þorlák</word>
<word pos="NOUN" lemma="biskup" />biskup</word>
<word pos="ADP" lemma="til" />til</word>
<word pos="NOUN" lemma="hjálp" />hjálpar</word>
<word pos="PRON" lemma="sig" />sér</word>
<word pos="PUNCT" lemma="." />.</word>
<word pos="ADP" lemma="eftir" />Eftir</word>
<word pos="PRON" lemma="það" />það</word>
<word pos="VERB" lemma="bregða" />brá</word>
<word pos="PRON" lemma="hún" />hún</word>
<word pos="NOUN" lemma="knífur" />knífi</word>
<word pos="CCONJ" lemma="og" />og</word>
<word pos="VERB" lemma="leita" />leitaði</word>
<word pos="PART" lemma="að" />að</word>
<word pos="VERB" lemma="skera" />skera</word>
<word pos="ADP" lemma="á" />á</word>
<word pos="NOUN" lemma="háls" />hálsinn</word>
<word pos="PRON" lemma="slíkur" />slíkt</word>
<word pos="SCONJ" lemma="er" />er</word>
<word pos="PRON" lemma="hún" />hún</word>
<word pos="AUX" lemma="mega" />mátti</word>
<word pos="PUNCT" lemma="." />.</word>
<word pos="CCONJ" lemma="en" />En</word>
<word pos="SCONJ" lemma="er" />er</word>
<word pos="PRON" lemma="hún" />henni</word>
<word pos="AUX" lemma="vera" />var</word>
<word pos="DET" lemma="lítill" />minnst</word>
<word pos="NOUN" lemma="von" />von</word>
<word pos="PUNCT" lemma="," />,</word>
<word pos="ADV" lemma="þá" />þá</word>
<word pos="VERB" lemma="falla" />féll</word>
<word pos="NOUN" lemma="griðungur" />griðungurinn</word>
<word pos="CCONJ" lemma="og" />og</word>
<word pos="VERB" lemma="rétta" />rétti</word>
<word pos="ADP" lemma="frá" />frá</word>
<word pos="PRON" lemma="sig" />sér</word>
<word pos="DET" lemma="allur" />alla</word>
<word pos="NOUN" lemma="fótur" />fætur</word>
<word pos="CCONJ" lemma="og" />og</word>
<word pos="VERB" lemma="hyggja" />hugði</word>
<word pos="PRON" lemma="hún" />hún</word>
<word pos="ADV" lemma="þá" />þá</word>
<word pos="NOUN" lemma="fjörbrot" />fjörbrot</word>
<word pos="ADP" lemma="á" />á</word>
<word pos="AUX" lemma="vera" />vera</word>
<word pos="PUNCT" lemma="." />.</word>
<word pos="VERB" lemma="koma" />Komst</word>
<word pos="PRON" lemma="hún" />hún</word>
<word pos="ADV" lemma="síðan" />síðan</word>
<word pos="ADV" lemma="nauðulega" />nauðulega</word>
<word pos="ADV" lemma="heim" />heim</word>
<word pos="PUNCT" lemma="." />.</word>
<word pos="CCONJ" lemma="en" />En</word>
<word pos="ADV" lemma="þá" />þá</word>
<word pos="SCONJ" lemma="er" />er</word>
<word pos="ADP" lemma="eftir" />eftir</word>
<word pos="NOUN" lemma="naut" />nautunum</word>
<word pos="AUX" lemma="vera" />var</word>
<word pos="VERB" lemma="fara" />farið</word>
<word pos="PUNCT" lemma="," />,</word>
<word pos="ADV" lemma="þá" />þá</word>
<word pos="VERB" lemma="ganga" />gekk</word>
<word pos="NOUN" lemma="griðungur" />griðungurinn</word>
<word pos="ADP" lemma="eftir" />eftir</word>
<word pos="NOUN" lemma="naut" />nautunum</word>
<word pos="ADV" lemma="svo" />svo</word>
<word pos="ADJ" lemma="hægur" />hægur</word>
<word pos="CCONJ" lemma="og" />og</word>
<word pos="ADJ" lemma="hýr" />hýr</word>
<word pos="SCONJ" lemma="að" />að</word>
<word pos="PRON" lemma="hann" />hann</word>
<word pos="VERB" lemma="gefa" />gaf</word>
<word pos="ADV" lemma="þá" />þá</word>
<word pos="ADP" lemma="að" />að</word>
<word pos="DET" lemma="enginn" />öngum</word>
<word pos="NOUN" lemma="maður" />manni</word>
<word pos="NOUN" lemma="gaumur" />gaum</word>
<word pos="PUNCT" lemma="." />.</word>
<word pos="CCONJ" lemma="en" />En</word>
<word pos="ADP" lemma="á" />á</word>
<word pos="VERB" lemma="sjá" />sá</word>
<word pos="ADP" lemma="of" />of</word>
<word pos="DET" lemma="allur" />allt</word>
<word pos="NOUN" lemma="sumar" />sumarið</word>
<word pos="ADP" lemma="eftir" />eftir</word>
<word pos="PRON" lemma="það" />það</word>
<word pos="SCONJ" lemma="er" />er</word>
<word pos="NOUN" lemma="atgangur" />atgangurinn</word>
<word pos="AUX" lemma="hafa" />hafði</word>
<word pos="AUX" lemma="vera" />verið</word>
<word pos="PUNCT" lemma="." />.</word>
<word pos="DET" lemma="sá" />Sá</word>
<word pos="NOUN" lemma="atburður" />atburður</word>
<word pos="VERB" lemma="verða" />varð</word>
<word pos="ADV" lemma="enn" />enn</word>
<word pos="SCONJ" lemma="að" />að</word>
<word pos="NOUN" lemma="maður" />maður</word>
<word pos="VERB" lemma="láta" />lét</word>
<word pos="VERB" lemma="gelda" />gelda</word>
<word pos="NOUN" lemma="hestur" />hest</word>
<word pos="SCONJ" lemma="er" />er</word>
<word pos="PRON" lemma="hann" />hann</word>
<word pos="VERB" lemma="eiga" />átti</word>
<word pos="PUNCT" lemma="," />,</word>
<word pos="ADJ" lemma="ungur" />ungan</word>
<word pos="CCONJ" lemma="og" />og</word>
<word pos="ADJ" lemma="góður" />góðan</word>
<word pos="PUNCT" lemma="." />.</word>
<word pos="CCONJ" lemma="en" />En</word>
<word pos="ADP" lemma="að" />að</word>
<word pos="NOUN" lemma="hestur" />hestinum</word>
<word pos="VERB" lemma="koma" />kom</word>
<word pos="NOUN" lemma="blóðrás" />blóðrás</word>
<word pos="DET" lemma="mikill" />mikil</word>
<word pos="PUNCT" lemma="." />.</word>
<word pos="CCONJ" lemma="en" />En</word>
<word pos="ADP" lemma="eftir" />eftir</word>
<word pos="PRON" lemma="það" />það</word>
<word pos="NOUN" lemma="sullur" />sullur</word>
<word pos="ADJ" lemma="æsilegur" />æsilegur</word>
<word pos="CCONJ" lemma="og" />og</word>
<word pos="VERB" lemma="svella" />svall</word>
<word pos="DET" lemma="allur" />allur</word>
<word pos="NOUN" lemma="kviður" />kviðurinn</word>
<word pos="ADP" lemma="á" />á</word>
<word pos="NOUN" lemma="hestur" />hestinum</word>
<word pos="ADP" lemma="svo" />svo</word>
<word pos="SCONJ" lemma="að" />að</word>
<word pos="ADV" lemma="ekki" />eigi</word>
<word pos="AUX" lemma="mega" />mátti</word>
<word pos="VERB" lemma="ganga" />ganga</word>
<word pos="ADP" lemma="að" />að</word>
<word pos="NOUN" lemma="matur" />mat</word>
<word pos="PRON" lemma="sig" />sér</word>
<word pos="ADP" lemma="of" />of</word>
<word pos="NOUN" lemma="síð" />síðir</word>
<word pos="CCONJ" lemma="og" />og</word>
<word pos="VERB" lemma="gera" />gerðust</word>
<word pos="ADP" lemma="að" />að</word>
<word pos="ADJ" lemma="vogfallur" />vogföll</word>
<word pos="DET" lemma="mikill" />mikil</word>
<word pos="CCONJ" lemma="og" />og</word>
<word pos="NOUN" lemma="hol" />hol</word>
<word pos="ADP" lemma="á" />á</word>
<word pos="ADV" lemma="svo" />svo</word>
<word pos="ADJ" lemma="stór" />stór</word>
<word pos="SCONJ" lemma="að" />að</word>
<word pos="NOUN" lemma="maður" />maður</word>
<word pos="AUX" lemma="mega" />mátti</word>
<word pos="VERB" lemma="stinga" />stinga</word>
<word pos="ADP" lemma="í" />í</word>
<word pos="NOUN" lemma="hnefi" />hnefa</word>
<word pos="PRON" lemma="sinn" />sínum</word>
<word pos="CCONJ" lemma="og" />og</word>
<word pos="ADV" lemma="þar" />þar</word>
<word pos="VERB" lemma="koma" />kom</word>
<word pos="ADP" lemma="of" />of</word>
<word pos="NOUN" lemma="síð" />síðir</word>
<word pos="SCONJ" lemma="að" />að</word>
<word pos="VERB" lemma="fúna" />fúnaði</word>
<word pos="NOUN" lemma="kviður" />kviðurinn</word>
<word pos="CCONJ" lemma="og" />og</word>
<word pos="AUX" lemma="vera" />voru</word>
<word pos="VERB" lemma="skera" />skornar</word>
<word pos="ADP" lemma="af" />af</word>
<word pos="DET" lemma="allur" />allar</word>
<word pos="NOUN" lemma="skauður" />skauðirnar</word>
<word pos="ADP" lemma="af" />af</word>
<word pos="NOUN" lemma="hestur" />hestinum</word>
<word pos="CCONJ" lemma="og" />og</word>
<word pos="VERB" lemma="þykja" />þótti</word>
<word pos="ADV" lemma="ekki" />eigi</word>
<word pos="NOUN" lemma="von" />von</word>
<word pos="PART" lemma="að" />að</word>
<word pos="VERB" lemma="lifa" />lifa</word>
<word pos="AUX" lemma="munu" />mundi</word>
<word pos="ADV" lemma="lengi" />lengi</word>
<word pos="PUNCT" lemma="." />.</word>
<word pos="ADP" lemma="eftir" />Eftir</word>
<word pos="PRON" lemma="það" />það</word>
<word pos="VERB" lemma="heita" />hét</word>
<word pos="DET" lemma="sá" />sá</word>
<word pos="SCONJ" lemma="er" />er</word>
<word pos="VERB" lemma="eiga" />átti</word>
<word pos="NOUN" lemma="hestur" />hestinn</word>
<word pos="PART" lemma="að" />að</word>
<word pos="VERB" lemma="gefa" />gefa</word>
<word pos="ADJ" lemma="hálfur" />hálfan</word>
<word pos="NOUN" lemma="hestur" />hestinn</word>
<word pos="DET" lemma="hinn" />hinum</word>
<word pos="ADJ" lemma="sæll" />sæla</word>
<word pos="PROPN" lemma="þorlákur" />Þorláki</word>
<word pos="NOUN" lemma="biskup" />biskupi</word>
<word pos="SCONJ" lemma="ef" />ef</word>
<word pos="ADP" lemma="fram" />fram</word>
<word pos="VERB" lemma="koma" />kæmist</word>
<word pos="PUNCT" lemma="." />.</word>
<word pos="ADV" lemma="síðan" />Síðan</word>
<word pos="VERB" lemma="færa" />færði</word>
<word pos="PRON" lemma="hann" />hann</word>
<word pos="ADP" lemma="á" />á</word>
<word pos="NOUN" lemma="braut" />braut</word>
<word pos="NOUN" lemma="hestur" />hestinn</word>
<word pos="PUNCT" lemma="," />,</word>
<word pos="CCONJ" lemma="en" />en</word>
<word pos="NOUN" lemma="hríð" />hríð</word>
<word pos="ADP" lemma="á" />á</word>
<word pos="DET" lemma="mikill" />mikil</word>
<word pos="PUNCT" lemma="." />.</word>
<word pos="CCONJ" lemma="en" />En</word>
<word pos="DET" lemma="hinn" />hinn</word>
<word pos="ADJ" lemma="sæll" />sæli</word>
<word pos="PROPN" lemma="þorlákur" />Þorlákur</word>
<word pos="NOUN" lemma="biskup" />biskup</word>
<word pos="VERB" lemma="gæta" />gætti</word>
<word pos="ADV" lemma="svo" />svo</word>
<word pos="ADP" lemma="til" />til</word>
<word pos="NOUN" lemma="hestur" />hestsins</word>
<word pos="SCONJ" lemma="að" />að</word>
<word pos="ADP" lemma="á" />á</word>
<word pos="DET" lemma="einn" />einum</word>
<word pos="ADJ" lemma="hálfur" />hálfum</word>
<word pos="NOUN" lemma="mánaður" />mánaði</word>
<word pos="VERB" lemma="verða" />varð</word>
<word pos="ADJ" lemma="alheill" />alheill</word>
<word pos="NOUN" lemma="hestur" />hesturinn</word>
<word pos="CCONJ" lemma="og" />og</word>
<word pos="ADV" lemma="svo" />svo</word>
<word pos="NOUN" lemma="skauður" />skauðirnar</word>
<word pos="ADP" lemma="á" />á</word>
<word pos="SCONJ" lemma="sem" />sem</word>
<word pos="PRON" lemma="annar" />öðrum</word>
<word pos="ADJ" lemma="geldur" />geldum</word>
<word pos="NOUN" lemma="hestur" />hestum</word>
<word pos="PUNCT" lemma="." />.</word>
<word pos="CCONJ" lemma="en" />En</word>
<word pos="DET" lemma="sá" />sá</word>
<word pos="VERB" lemma="leysa" />leysti</word>
<word pos="ADV" lemma="síðan" />síðan</word>
<word pos="NOUN" lemma="hestur" />hestinn</word>
<word pos="ADP" lemma="til" />til</word>
<word pos="PRON" lemma="sig" />sín</word>
<word pos="ADP" lemma="of" />of</word>
<word pos="NOUN" lemma="vor" />vorið</word>
<word pos="SCONJ" lemma="er" />er</word>
<word pos="VERB" lemma="heita" />heitið</word>
<word pos="AUX" lemma="hafa" />hafði</word>
<word pos="CCONJ" lemma="og" />og</word>
<word pos="VERB" lemma="enda" />endi</word>
<word pos="ADV" lemma="vel" />vel</word>
<word pos="NOUN" lemma="heit" />heit</word>
<word pos="PRON" lemma="sinn" />sitt</word>
<word pos="ADP" lemma="eftir" />eftir</word>
<word pos="NOUN" lemma="ráð" />ráði</word>
<word pos="PROPN" lemma="páll" />Páls</word>
<word pos="NOUN" lemma="biskup" />biskups</word>
<word pos="CCONJ" lemma="og" />og</word>
<word pos="VERB" lemma="þökka" />þökkuðu</word>
<word pos="NOUN" lemma="maður" />menn</word>
<word pos="PROPN" lemma="guð" />guði</word>
<word pos="DET" lemma="þessi" />þessa</word>
<word pos="NOUN" lemma="jarteinn" />jartein</word>
<word pos="CCONJ" lemma="og" />og</word>
<word pos="DET" lemma="hinn" />hinum</word>
<word pos="ADJ" lemma="sæll" />sæla</word>
<word pos="PROPN" lemma="þorlákur" />Þorláki</word>
<word pos="NOUN" lemma="biskup" />biskupi</word>
<word pos="PUNCT" lemma="." />.</word>
<word pos="NOUN" lemma="maður" />Maður</word>
<word pos="VERB" lemma="fara" />fór</word>
<word pos="DET" lemma="þessi" />þenna</word>
<word pos="DET" lemma="hinn" />hinn</word>
<word pos="ADJ" lemma="samur" />sama</word>
<word pos="NOUN" lemma="vetur" />vetur</word>
<word pos="ADP" lemma="eftir" />eftir</word>
<word pos="NOUN" lemma="upptekning" />upptekning</word>
<word pos="DET" lemma="hinn" />hins</word>
<word pos="ADJ" lemma="sæll" />sæla</word>
<word pos="PROPN" lemma="þorlákur" />Þorláks</word>
<word pos="NOUN" lemma="biskup" />biskups</word>
<word pos="ADV" lemma="óvarlega" />óvarlega</word>
<word pos="ADP" lemma="með" />með</word>
<word pos="NOUN" lemma="hestur" />hest</word>
<word pos="CCONJ" lemma="og" />og</word>
<word pos="VERB" lemma="bresta" />brast</word>
<word pos="ADP" lemma="niður" />niður</word>
<word pos="NOUN" lemma="ís" />ís</word>
<word pos="ADP" lemma="undir" />undir</word>
<word pos="DET" lemma="allur" />öllum</word>
<word pos="ADV" lemma="saman" />saman</word>
<word pos="ADV" lemma="þar" />þar</word>
<word pos="SCONJ" lemma="er" />er</word>
<word pos="NOUN" lemma="vatnfall" />vatnfall</word>
<word pos="AUX" lemma="vera" />var</word>
<word pos="ADV" lemma="undir" />undir</word>
<word pos="CCONJ" lemma="og" />og</word>
<word pos="NOUN" lemma="djúp" />djúp</word>
<word pos="PUNCT" lemma="." />.</word>
<word pos="VERB" lemma="koma" />Komst</word>
<word pos="NOUN" lemma="maður" />maðurinn</word>
<word pos="ADV" lemma="brátt" />brátt</word>
<word pos="ADP" lemma="upp" />upp</word>
<word pos="ADP" lemma="úr" />úr</word>
<word pos="NOUN" lemma="vök" />vökinni</word>
<word pos="CCONJ" lemma="en" />en</word>
<word pos="NOUN" lemma="hestur" />hesturinn</word>
<word pos="VERB" lemma="koma" />komst</word>
<word pos="ADV" lemma="ekki" />eigi</word>
<word pos="ADP" lemma="upp" />upp</word>
<word pos="PUNCT" lemma="." />.</word>
<word pos="VERB" lemma="fara" />Fór</word>
<word pos="NOUN" lemma="maður" />maðurinn</word>
<word pos="ADV" lemma="síðan" />síðan</word>
<word pos="ADV" lemma="heim" />heim</word>
<word pos="ADP" lemma="til" />til</word>
<word pos="NOUN" lemma="bær" />bæjarins</word>
<word pos="ADV" lemma="skyndilega" />skyndilega</word>
<word pos="CCONJ" lemma="og" />og</word>
<word pos="VERB" lemma="kalla" />kallaði</word>
<word pos="ADP" lemma="á" />á</word>
<word pos="NOUN" lemma="maður" />menn</word>
<word pos="CCONJ" lemma="og" />og</word>
<word pos="VERB" lemma="grípa" />greip</word>
<word pos="NOUN" lemma="járnsleggja" />járnsleggju</word>
<word pos="ADP" lemma="í" />í</word>
<word pos="NOUN" lemma="hönd" />hönd</word>
<word pos="PRON" lemma="sig" />sér</word>
<word pos="CCONJ" lemma="og" />og</word>
<word pos="VERB" lemma="renna" />rann</word>
<word pos="ADP" lemma="fyrir" />fyrir</word>
<word pos="CCONJ" lemma="og" />og</word>
<word pos="VERB" lemma="brjóta" />braut</word>
<word pos="NOUN" lemma="ís" />ísinn</word>
<word pos="CCONJ" lemma="en" />en</word>
<word pos="VERB" lemma="víða" />víddi</word>
<word pos="NOUN" lemma="vök" />vökina</word>
<word pos="CCONJ" lemma="og" />og</word>
<word pos="SCONJ" lemma="er" />er</word>
<word pos="PRON" lemma="hann" />honum</word>
<word pos="AUX" lemma="vera" />var</word>
<word pos="DET" lemma="lítill" />minnst</word>
<word pos="NOUN" lemma="von" />von</word>
<word pos="ADV" lemma="þá" />þá</word>
<word pos="VERB" lemma="sleppa" />slapp</word>
<word pos="NOUN" lemma="sleggja" />sleggjan</word>
<word pos="ADP" lemma="úr" />úr</word>
<word pos="NOUN" lemma="hönd" />hendi</word>
<word pos="PRON" lemma="hann" />honum</word>
<word pos="ADP" lemma="í" />í</word>
<word pos="NOUN" lemma="vök" />vökina</word>
<word pos="CCONJ" lemma="og" />og</word>
<word pos="NOUN" lemma="djúp" />djúpið</word>
<word pos="PUNCT" lemma="." />.</word>
<word pos="VERB" lemma="koma" />Komu</word>
<word pos="ADV" lemma="þá" />þá</word>
<word pos="NOUN" lemma="maður" />menn</word>
<word pos="ADP" lemma="að" />að</word>
<word pos="CCONJ" lemma="og" />og</word>
<word pos="VERB" lemma="koma" />komst</word>
<word pos="ADV" lemma="þá" />þá</word>
<word pos="ADP" lemma="upp" />upp</word>
<word pos="NOUN" lemma="hestur" />hesturinn</word>
<word pos="ADV" lemma="brátt" />brátt</word>
<word pos="PUNCT" lemma="." />.</word>
<word pos="CCONJ" lemma="en" />En</word>
<word pos="NOUN" lemma="sleggja" />sleggjan</word>
<word pos="VERB" lemma="ná" />náðist</word>
<word pos="ADV" lemma="ekki" />ekki</word>
<word pos="CCONJ" lemma="og" />og</word>
<word pos="VERB" lemma="merkja" />merktu</word>
<word pos="PRON" lemma="hann" />þeir</word>
<word pos="ADP" lemma="til" />til</word>
<word pos="ADV" lemma="hvar" />hvar</word>
<word pos="NOUN" lemma="sleggja" />sleggjunnar</word>
<word pos="AUX" lemma="vera" />var</word>
<word pos="NOUN" lemma="von" />von</word>
<word pos="PUNCT" lemma="," />,</word>
<word pos="VERB" lemma="setja" />settu</word>
<word pos="ADP" lemma="upp" />upp</word>
<word pos="NOUN" lemma="drangsteinn" />drangstein</word>
<word pos="ADP" lemma="á" />á</word>
<word pos="NOUN" lemma="land" />landinu</word>
<word pos="ADV" lemma="gagnvert" />gagnvert</word>
<word pos="CCONJ" lemma="og" />og</word>
<word pos="ADV" lemma="ekki" />eigi</word>
<word pos="ADV" lemma="allnær" />allnær</word>
<word pos="NOUN" lemma="vatnfall" />vatnfallinu</word>
<word pos="CCONJ" lemma="og" />og</word>
<word pos="VERB" lemma="ganga" />gengu</word>
<word pos="ADV" lemma="heim" />heim</word>
<word pos="ADV" lemma="síðan" />síðan</word>
<word pos="PUNCT" lemma="." />.</word>
<word pos="CCONJ" lemma="en" />En</word>
<word pos="PRON" lemma="það" />þeim</word>
<word pos="SCONJ" lemma="er" />er</word>
<word pos="NOUN" lemma="sleggja" />sleggjuna</word>
<word pos="AUX" lemma="hafa" />hafði</word>
<word pos="ADP" lemma="niður" />niður</word>
<word pos="VERB" lemma="fella" />fellt</word>
<word pos="VERB" lemma="þykja" />þótti</word>
<word pos="ADJ" lemma="illur" />ill</word>
<word pos="NOUN" lemma="slysför" />slysför</word>
<word pos="PRON" lemma="sinn" />sín</word>
<word pos="CCONJ" lemma="en" />en</word>
<word pos="NOUN" lemma="fjárskaði" />fjárskaði</word>
<word pos="NOUN" lemma="búandi" />búanda</word>
<word pos="CCONJ" lemma="og" />og</word>
<word pos="VERB" lemma="heita" />hét</word>
<word pos="ADV" lemma="síðan" />síðan</word>
<word pos="ADP" lemma="á" />á</word>
<word pos="DET" lemma="hinn" />hinn</word>
<word pos="ADJ" lemma="sæll" />sæla</word>
<word pos="PROPN" lemma="þorlákur" />Þorlák</word>
<word pos="NOUN" lemma="biskup" />biskup</word>
<word pos="SCONJ" lemma="að" />að</word>
<word pos="NOUN" lemma="sleggja" />sleggjan</word>
<word pos="AUX" lemma="skulu" />skyldi</word>
<word pos="VERB" lemma="ná" />nást</word>
<word pos="PUNCT" lemma="." />.</word>
<word pos="CCONJ" lemma="en" />En</word>
<word pos="DET" lemma="fár" />fám</word>
<word pos="NOUN" lemma="nótt" />nóttum</word>
<word pos="ADV" lemma="síður" />síðar</word>
<word pos="VERB" lemma="koma" />kom</word>
<word pos="PRON" lemma="hann" />hann</word>
<word pos="ADP" lemma="til" />til</word>
<word pos="ADV" lemma="þar" />þar</word>
<word pos="SCONJ" lemma="er" />er</word>
<word pos="NOUN" lemma="sleggja" />sleggjan</word>
<word pos="AUX" lemma="hafa" />hafði</word>
<word pos="VERB" lemma="týna" />týnst</word>
<word pos="CCONJ" lemma="og" />og</word>
<word pos="ADV" lemma="þá" />þá</word>
<word pos="SCONJ" lemma="er" />er</word>
<word pos="PRON" lemma="hann" />hann</word>
<word pos="AUX" lemma="vilja" />vildi</word>
<word pos="ADP" lemma="að" />að</word>
<word pos="VERB" lemma="hyggja" />hyggja</word>
<word pos="SCONJ" lemma="að" />að</word>
<word pos="ADV" lemma="ekki" />eigi</word>
<word pos="VERB" lemma="falla" />félli</word>
<word pos="NOUN" lemma="marksteinn" />marksteinninn</word>
<word pos="PUNCT" lemma="," />,</word>
<word pos="ADV" lemma="þá" />þá</word>
<word pos="VERB" lemma="standa" />stóð</word>
<word pos="ADV" lemma="þar" />þar</word>
<word pos="NOUN" lemma="sleggja" />sleggjan</word>
<word pos="ADP" lemma="við" />við</word>
<word pos="NOUN" lemma="steinn" />steininn</word>
<word pos="SCONJ" lemma="sem" />sem</word>
<word pos="NOUN" lemma="maður" />maður</word>
<word pos="AUX" lemma="hafa" />hefði</word>
<word pos="VERB" lemma="nýsetja" />nýsett</word>
<word pos="ADP" lemma="niður" />niður</word>
<word pos="PUNCT" lemma="." />.</word>
<word pos="VERB" lemma="verða" />Varð</word>
<word pos="PRON" lemma="hann" />hann</word>
<word pos="ADV" lemma="síðan" />síðan</word>
<word pos="NOUN" lemma="allshugur" />allshugar</word>
<word pos="ADJ" lemma="feginn" />feginn</word>
<word pos="CCONJ" lemma="og" />og</word>
<word pos="VERB" lemma="taka" />tók</word>
<word pos="NOUN" lemma="sleggja" />sleggjuna</word>
<word pos="CCONJ" lemma="og" />og</word>
<word pos="VERB" lemma="hafa" />hafði</word>
<word pos="ADV" lemma="heim" />heim</word>
<word pos="CCONJ" lemma="og" />og</word>
<word pos="VERB" lemma="segja" />sagði</word>
<word pos="DET" lemma="þessi" />þessa</word>
<word pos="ADJ" lemma="fagurlegur" />fagurlega</word>
<word pos="NOUN" lemma="jartein" />jartein</word>
<word pos="DET" lemma="allur" />öllum</word>
<word pos="NOUN" lemma="maður" />mönnum</word>
<word pos="PRON" lemma="það" />þeim</word>
<word pos="SCONJ" lemma="er" />er</word>
<word pos="ADP" lemma="við" />við</word>
<word pos="AUX" lemma="vera" />voru</word>
<word pos="ADJ" lemma="staddur" />staddir</word>
<word pos="CCONJ" lemma="og" />og</word>
<word pos="VERB" lemma="lofa" />lofuðu</word>
<word pos="DET" lemma="allur" />allir</word>
<word pos="PROPN" lemma="guð" />guð</word>
<word pos="CCONJ" lemma="og" />og</word>
<word pos="DET" lemma="hinn" />hinn</word>
<word pos="ADJ" lemma="sæll" />sæla</word>
<word pos="PROPN" lemma="þorlákur" />Þorlák</word>
<word pos="NOUN" lemma="biskup" />biskup</word>
<word pos="PUNCT" lemma="." />.</word>
<word pos="PRON" lemma="annar" />Annar</word>
<word pos="NOUN" lemma="atburður" />atburður</word>
<word pos="VERB" lemma="verða" />varð</word>
<word pos="ADV" lemma="enn" />enn</word>
<word pos="DET" lemma="þessi" />þessum</word>
<word pos="ADJ" lemma="glíkur" />glíkur</word>
<word pos="ADP" lemma="í" />í</word>
<word pos="PROPN" lemma="skálaholt" />Skálaholti</word>
<word pos="PUNCT" lemma="." />.</word>
<word pos="ADV" lemma="þar" />Þar</word>
<word pos="VERB" lemma="brotna" />brotnaði</word>
<word pos="NOUN" lemma="þelahögg" />þelahögg</word>
<word pos="SCONJ" lemma="er" />er</word>
<word pos="NOUN" lemma="gröf" />gröf</word>
<word pos="AUX" lemma="vera" />var</word>
<word pos="VERB" lemma="grafa" />grafin</word>
<word pos="PUNCT" lemma="." />.</word>
<word pos="CCONJ" lemma="en" />En</word>
<word pos="ADV" lemma="þá" />þá</word>
<word pos="AUX" lemma="vera" />var</word>
<word pos="VERB" lemma="fá" />fengin</word>
<word pos="ADP" lemma="til" />til</word>
<word pos="NOUN" lemma="öx" />öx</word>
<word pos="DET" lemma="mikill" />mikil</word>
<word pos="PART" lemma="að" />að</word>
<word pos="VERB" lemma="höggva" />höggva</word>
<word pos="NOUN" lemma="þela" />þelann</word>
<word pos="PUNCT" lemma="." />.</word>
<word pos="CCONJ" lemma="en" />En</word>
<word pos="SCONJ" lemma="er" />er</word>
<word pos="NOUN" lemma="gröf" />gröfin</word>
<word pos="AUX" lemma="vera" />var</word>
<word pos="VERB" lemma="grafa" />grafin</word>
<word pos="ADP" lemma="til" />til</word>
<word pos="ADV" lemma="loks" />loks</word>
<word pos="PUNCT" lemma="," />,</word>
<word pos="ADV" lemma="þá" />þá</word>
<word pos="VERB" lemma="gleyma" />gleymdist</word>
<word pos="NOUN" lemma="öxi" />öxin</word>
<word pos="CCONJ" lemma="og" />og</word>
<word pos="AUX" lemma="vera" />var</word>
<word pos="NOUN" lemma="angi" />öngum</word>
<word pos="VERB" lemma="selja" />seld</word>
<word pos="ADP" lemma="til" />til</word>
<word pos="NOUN" lemma="varðveisla" />varðveislu</word>
<word pos="PUNCT" lemma="." />.</word>
<word pos="CCONJ" lemma="en" />En</word>
<word pos="SCONJ" lemma="er" />er</word>
<word pos="ADV" lemma="ekki" />eigi</word>
<word pos="AUX" lemma="vera" />var</word>
<word pos="VERB" lemma="sakna" />saknað</word>
<word pos="ADV" lemma="fyrr" />fyrr</word>
<word pos="SCONJ" lemma="en" />en</word>
<word pos="NUM" lemma="tveir" />tveim</word>
<word pos="NOUN" lemma="nótt" />nóttum</word>
<word pos="CCONJ" lemma="eða" />eða</word>
<word pos="NUM" lemma="þrír" />þrimur</word>
<word pos="ADV" lemma="síðan" />síðan</word>
<word pos="CCONJ" lemma="en" />en</word>
<word pos="AUX" lemma="vera" />verið</word>
<word pos="VERB" lemma="hafa" />hafði</word>
<word pos="DET" lemma="margur" />margt</word>

найти: 	заменить: 
найт:^(\S+)\W(\S+)\W(\S+)заменить:\3 \2 \1
найти:(.*) (.*) (.*)заменить:<word pos="\1" lemma="\2" />\3</word>
найти:^\nзаменить:
 
